Metadata-Version: 2.1
Name: hawkes
Version: 1.0.0
Summary: a python package for simulation and inference of Hawkes processeses
Home-page: https://github.com/omitakahiro/Hawkes
Author: Takahiro Omi
Author-email: takahiro.omi.em@gmail.com
License: UNKNOWN
Project-URL: Bug Tracker, https://github.com/omitakahiro/Hawkes/issues
Platform: UNKNOWN
Classifier: Programming Language :: Python :: 3
Classifier: License :: OSI Approved :: MIT License
Classifier: Operating System :: OS Independent
Requires-Python: >=3.6
